radicalbit_ai_monitoring/__init__.py
radicalbit_ai_monitoring/cli.py
radicalbit_ai_monitoring/commands/info.py
radicalbit_ai_monitoring/commands/platform/__init__.py
radicalbit_ai_monitoring/commands/platform/install.py
radicalbit_ai_monitoring/commands/platform/platform.py
radicalbit_ai_monitoring/commands/platform/stop.py
radicalbit_ai_monitoring/commands/platform/uninstall.py
radicalbit_ai_monitoring/commands/platform/up.py
radicalbit_ai_monitoring/models/__init__.py
radicalbit_ai_monitoring/models/compose_service.py
radicalbit_ai_monitoring/models/docker_status.py
radicalbit_ai_monitoring/resources/docker/init-data/init_db.sql
radicalbit_ai_monitoring/resources/docker/init-data/mirror_files.sh
radicalbit_ai_monitoring/resources/docker/init-data/quickstarts/data/binary_classification/current1-income.csv
radicalbit_ai_monitoring/resources/docker/init-data/quickstarts/data/binary_classification/reference-income.csv
radicalbit_ai_monitoring/resources/docker/init-data/quickstarts/data/multiclass-classification/3_classes_current1.csv
radicalbit_ai_monitoring/resources/docker/init-data/quickstarts/data/multiclass-classification/3_classes_reference.csv
radicalbit_ai_monitoring/resources/docker/init-data/quickstarts/data/regression/regression_abalone_current1.csv
radicalbit_ai_monitoring/resources/docker/init-data/quickstarts/data/regression/regression_abalone_reference.csv
radicalbit_ai_monitoring/resources/docker/k3s_data/init/entrypoint.sh
radicalbit_ai_monitoring/resources/docker/k3s_data/manifests/spark-init.yaml
radicalbit_ai_monitoring/resources/docker/otel-collector/otel-collector-config.yaml
radicalbit_ai_monitoring/resources/docker-compose-local.yaml
radicalbit_ai_monitoring/services/__init__.py
radicalbit_ai_monitoring/services/docker.py
radicalbit_ai_monitoring/services/fs.py
radicalbit_ai_monitoring-0.12.0.dist-info/LICENSE
radicalbit_ai_monitoring-0.12.0.dist-info/METADATA
radicalbit_ai_monitoring-0.12.0.dist-info/WHEEL
radicalbit_ai_monitoring-0.12.0.dist-info/entry_points.txt
radicalbit_ai_monitoring-0.12.0.dist-info/RECORD
